pl_horizontal-0.1.6.dist-info/METADATA
pl_horizontal-0.1.6.dist-info/WHEEL
pl_horizontal.libs/libgcc_s-27e5a392.so.1
pl_horizontal/__init__.py
pl_horizontal/_expr_builders.py
pl_horizontal/_internal.cpython-313t-i386-linux-musl.so
pl_horizontal/_internal.pyi
pl_horizontal/typing.py
pl_horizontal-0.1.6.dist-info/RECORD
