Metadata-Version: 2.4
Name: pl-horizontal
Version: 0.1.6
Classifier: Programming Language :: Rust
Classifier: Programming Language :: Python :: Implementation :: CPython
Requires-Dist: maturin>=1.9.3
Requires-Dist: polars<=1.32.1
Requires-Python: >=3.12
